django_test_model_builder/__init__.py
django_test_model_builder/builders.py
django_test_model_builder/exceptions.py
django_test_model_builder-0.0.2.dist-info/LICENSE
django_test_model_builder-0.0.2.dist-info/METADATA
django_test_model_builder-0.0.2.dist-info/WHEEL
django_test_model_builder-0.0.2.dist-info/top_level.txt
django_test_model_builder-0.0.2.dist-info/RECORD
