Metadata-Version: 2.1
Name: django-test-model-builder
Version: 0.0.2
Summary: A small python / django model designed to decouple creation of models for testing from the creation of models in production to make updating tests less painful.
Home-page: https://github.com/publons/django-test-model-builder
Author: Matthew Betts, Aidan Houlihan
Author-email: aidan@publons.com
License: MIT License
Platform: UNKNOWN
Classifier: Environment :: Web Environment
Classifier: Framework :: Django
Classifier: Intended Audience :: Developers
Classifier: License :: OSI Approved :: BSD License
Classifier: Operating System :: OS Independent
Classifier: Programming Language :: Python
Classifier: Programming Language :: Python :: 3.0
Classifier: Programming Language :: Python :: 3.6
Classifier: Topic :: Internet :: WWW/HTTP
Classifier: Topic :: Internet :: WWW/HTTP :: Dynamic Content
Requires-Dist: Django
